qoqo_strawberry_fields/__init__.py
qoqo_strawberry_fields/__version__.py
qoqo_strawberry_fields/backend.py
qoqo_strawberry_fields/interface.py
qoqo_strawberry_fields/post_processing.py
qoqo_strawberry_fields-0.3.1.dist-info/LICENSE
qoqo_strawberry_fields-0.3.1.dist-info/METADATA
qoqo_strawberry_fields-0.3.1.dist-info/WHEEL
qoqo_strawberry_fields-0.3.1.dist-info/top_level.txt
qoqo_strawberry_fields-0.3.1.dist-info/RECORD
