Metadata-Version: 2.2
Name: qoqo_strawberry_fields
Version: 0.3.1
Author-email: HQS Quantum Simulation GmbH <info@quantumsimulations.de>
Maintainer-email: Kirsten Bark <kirsten.bark@quantumsimulations.de>
License:                                  Apache License
Requires-Python: >=3.9
License-File: LICENSE
Requires-Dist: pydantic
Requires-Dist: qoqo>=1.17
Requires-Dist: strawberryfields
Requires-Dist: tensorflow
Requires-Dist: numpy
Requires-Dist: scipy<1.14,>=1.10
Provides-Extra: tests
Requires-Dist: coverage; extra == "tests"
Requires-Dist: pytest; extra == "tests"
Provides-Extra: dev
Requires-Dist: bandit; extra == "dev"
Requires-Dist: black; extra == "dev"
Requires-Dist: darglint; extra == "dev"
Requires-Dist: flake8; extra == "dev"
Requires-Dist: flake8-bandit; extra == "dev"
Requires-Dist: flake8-bugbear; extra == "dev"
Requires-Dist: flake8-pydocstyle; extra == "dev"
Requires-Dist: flake8-pyproject; extra == "dev"
Requires-Dist: mypy; extra == "dev"
Requires-Dist: ruff; extra == "dev"
Provides-Extra: docs
Requires-Dist: sphinx>=2.1; extra == "docs"
Requires-Dist: nbsphinx; extra == "docs"
Requires-Dist: pygments; extra == "docs"
Requires-Dist: recommonmark; extra == "docs"
Requires-Dist: myst_parser; extra == "docs"
Requires-Dist: sphinx_rtd_theme; extra == "docs"
Requires-Dist: tomli; extra == "docs"
